django_viewedmodels-0.1.26.dist-info/DESCRIPTION.rst
django_viewedmodels-0.1.26.dist-info/METADATA
django_viewedmodels-0.1.26.dist-info/RECORD
django_viewedmodels-0.1.26.dist-info/WHEEL
django_viewedmodels-0.1.26.dist-info/metadata.json
django_viewedmodels-0.1.26.dist-info/top_level.txt
viewedmodels/__init__.py
viewedmodels/apps.py
viewedmodels/helpers.py
viewedmodels/models.py
viewedmodels/management/commands/__init__.py
viewedmodels/management/commands/recreate_viewed_models.py
viewedmodels/management/commands/refresh_viewed_models.py
viewedmodels/management/commands/vacuum_viewed_models.py
