Metadata-Version: 2.0
Name: django-viewedmodels
Version: 0.1.26
Summary: A Django app to define Postgres Views as Models
Home-page: https://github.com/joshbrooks/django_viewedmodels/
Author: Joshua Brooks
Author-email: josh@catalpa.io
License: GPLv3
Download-URL: https://github.com/joshbrooks/django_viewedmodels/archive/0.1.26.tar.gz
Platform: UNKNOWN
Classifier: Development Status :: 4 - Beta
Classifier: Environment :: Web Environment
Classifier: Framework :: Django
Classifier: Intended Audience :: Developers
Classifier: Operating System :: OS Independent
Classifier: Programming Language :: Python
Classifier: Programming Language :: Python :: 3
Classifier: Topic :: Internet :: WWW/HTTP
Classifier: Topic :: Internet :: WWW/HTTP :: Dynamic Content
Requires-Dist: toposort
